examples/__init__.py
examples/atomic_fields.py
examples/compound_fields.py
examples/model_fields.py
examples/schematics_field.py
stereotype/__init__.py
stereotype/meta.py
stereotype/model.py
stereotype/roles.py
stereotype/utils.py
stereotype/contrib/__init__.py
stereotype/contrib/schematics.py
stereotype/fields/__init__.py
stereotype/fields/annotations.py
stereotype/fields/atomic.py
stereotype/fields/base.py
stereotype/fields/compound.py
stereotype/fields/model.py
stereotype/fields/serializable.py
stereotype-1.5.4.dist-info/LICENSE
stereotype-1.5.4.dist-info/METADATA
stereotype-1.5.4.dist-info/WHEEL
stereotype-1.5.4.dist-info/top_level.txt
stereotype-1.5.4.dist-info/RECORD
