Metadata-Version: 2.1
Name: stereotype
Version: 1.5.4
Summary: Models for conversion and validation of rich data structures.
Home-page: https://github.com/petee-d/stereotype
Author: Peter Dolák
Author-email: peter@dolak.sk
Classifier: Programming Language :: Python :: 3
Classifier: License :: OSI Approved :: MIT License
Classifier: Operating System :: OS Independent
Requires-Python: >=3.8
License-File: LICENSE
